{
  "statements": [
    {
      "statement": "CREATE CONSTRAINT ON (n:CEDAR) ASSERT n._id IS UNIQUE"
    },
    {
      "statement": "CREATE INDEX ON :CEDAR(ownedBy)"
    },
    {
      "statement": "CREATE INDEX ON :CEDAR(nodeType)"
    },
    {
      "statement": "CREATE INDEX ON :CEDAR(nodeSortOrder)"
    },
    {
      "statement": "CREATE INDEX ON :CEDAR(schema_name)"
    },
    {
      "statement": "CREATE CONSTRAINT ON (n:Folder) ASSERT n._id IS UNIQUE"
    },
    {
      "statement": "CREATE INDEX ON :Folder(ownedBy)"
    },
    {
      "statement": "CREATE INDEX ON :Folder(nodeType)"
    },
    {
      "statement": "CREATE INDEX ON :Folder(nodeSortOrder)"
    },
    {
      "statement": "CREATE INDEX ON :Folder(schema_name)"
    },
    {
      "statement": "CREATE INDEX ON :Folder(createdOnTS)"
    },
    {
      "statement": "CREATE INDEX ON :Folder(lastUpdatedOnTS)"
    },
    {
      "statement": "CREATE INDEX ON :Folder(isRoot)"
    },
    {
      "statement": "CREATE INDEX ON :Folder(isSystem)"
    },
    {
      "statement": "CREATE INDEX ON :Folder(isUserHome)"
    },
    {
      "statement": "CREATE INDEX ON :Folder(homeOf)"
    },
    {
      "statement": "CREATE CONSTRAINT ON (n:Group) ASSERT n._id IS UNIQUE"
    },
    {
      "statement": "CREATE INDEX ON :Group(schema_name)"
    },
    {
      "statement": "CREATE INDEX ON :Group(specialGroup)"
    },
    {
      "statement": "CREATE CONSTRAINT ON (n:User) ASSERT n._id IS UNIQUE"
    },
    {
      "statement": "CREATE CONSTRAINT ON (n:Resource) ASSERT n._id IS UNIQUE"
    },
    {
      "statement": "CREATE INDEX ON :Resource(ownedBy)"
    },
    {
      "statement": "CREATE INDEX ON :Resource(nodeType)"
    },
    {
      "statement": "CREATE INDEX ON :Resource(nodeSortOrder)"
    },
    {
      "statement": "CREATE INDEX ON :Resource(schema_name)"
    },
    {
      "statement": "CREATE INDEX ON :Resource(createdOnTS)"
    },
    {
      "statement": "CREATE INDEX ON :Resource(lastUpdatedOnTS)"
    },
    {
      "statement": "CREATE INDEX ON :Resource(schema_isBasedOn)"
    },
    {
      "statement": "CREATE INDEX ON :Resource(pav_derivedFrom)"
    },
    {
      "statement": "CREATE INDEX ON :Resource(pav_version)"
    },
    {
      "statement": "CREATE INDEX ON :Resource(bibo_status)"
    },
    {
      "statement": "CREATE INDEX ON :Resource(isLatestVersion)"
    },
    {
      "statement": "CREATE CONSTRAINT ON (n:Field) ASSERT n._id IS UNIQUE"
    },
    {
      "statement": "CREATE CONSTRAINT ON (n:Element) ASSERT n._id IS UNIQUE"
    },
    {
      "statement": "CREATE CONSTRAINT ON (n:Template) ASSERT n._id IS UNIQUE"
    },
    {
      "statement": "CREATE CONSTRAINT ON (n:Instance) ASSERT n._id IS UNIQUE"
    }
  ]
}